kubeflow_pipeline/__init__.py
kubeflow_pipeline/__main__.py
kubeflow_pipeline/base.py
kubeflow_pipeline/cli.py
kubeflow_pipeline-0.0.0.dist-info/LICENSE
kubeflow_pipeline-0.0.0.dist-info/METADATA
kubeflow_pipeline-0.0.0.dist-info/WHEEL
kubeflow_pipeline-0.0.0.dist-info/entry_points.txt
kubeflow_pipeline-0.0.0.dist-info/top_level.txt
kubeflow_pipeline-0.0.0.dist-info/RECORD
