Metadata-Version: 2.1
Name: kubeflow_pipeline
Version: 0.0.0
Summary: Awesome kubeflow_pipeline created by ajperry2
Home-page: https://github.com/ajperry2/kubeflow_pipeline/
Author: ajperry2
License-File: LICENSE
Provides-Extra: test
Requires-Dist: pytest; extra == "test"
Requires-Dist: coverage; extra == "test"
Requires-Dist: flake8; extra == "test"
Requires-Dist: black; extra == "test"
Requires-Dist: isort; extra == "test"
Requires-Dist: pytest-cov; extra == "test"
Requires-Dist: mypy; extra == "test"
Requires-Dist: gitchangelog; extra == "test"
Requires-Dist: mkdocs; extra == "test"
